strain_relief/__init__.py
strain_relief/compute_strain.py
strain_relief/calculators/__init__.py
strain_relief/calculators/_mmff94.py
strain_relief/calculators/_nnp.py
strain_relief/cmdline/__init__.py
strain_relief/cmdline/_strain_relief.py
strain_relief/conformers/__init__.py
strain_relief/conformers/_rdkit_generation.py
strain_relief/constants/__init__.py
strain_relief/constants/_str.py
strain_relief/constants/_units.py
strain_relief/energy_eval/__init__.py
strain_relief/energy_eval/_energy_eval.py
strain_relief/energy_eval/_mmff94.py
strain_relief/energy_eval/_nnp.py
strain_relief/hydra_config/__init__.py
strain_relief/hydra_config/default.yaml
strain_relief/hydra_config/conformers/default.yaml
strain_relief/hydra_config/energy_eval/default.yaml
strain_relief/hydra_config/energy_eval/fairchem.yaml
strain_relief/hydra_config/energy_eval/mace.yaml
strain_relief/hydra_config/energy_eval/mmff94.yaml
strain_relief/hydra_config/energy_eval/mmff94s.yaml
strain_relief/hydra_config/experiment/fairchem.yaml
strain_relief/hydra_config/experiment/mace.yaml
strain_relief/hydra_config/experiment/mmff94s.yaml
strain_relief/hydra_config/io/default.yaml
strain_relief/hydra_config/minimisation/fairchem.yaml
strain_relief/hydra_config/minimisation/mace.yaml
strain_relief/hydra_config/minimisation/mmff94.yaml
strain_relief/hydra_config/minimisation/mmff94s.yaml
strain_relief/hydra_config/model/fairchem.yaml
strain_relief/hydra_config/model/mace.yaml
strain_relief/io/__init__.py
strain_relief/io/_io.py
strain_relief/io/utils_mol_format.py
strain_relief/io/utils_s3.py
strain_relief/minimisation/__init__.py
strain_relief/minimisation/_minimisation.py
strain_relief/minimisation/_mmff94.py
strain_relief/minimisation/_nnp.py
strain_relief/minimisation/utils_bfgs.py
strain_relief/minimisation/utils_minimisation.py
strain_relief/types/__init__.py
strain_relief/types/_types.py
strain_relief-0.5.dist-info/licenses/LICENSE
strain_relief-0.5.dist-info/METADATA
strain_relief-0.5.dist-info/WHEEL
strain_relief-0.5.dist-info/entry_points.txt
strain_relief-0.5.dist-info/top_level.txt
strain_relief-0.5.dist-info/RECORD
