Metadata-Version: 2.4
Name: strain-relief
Version: 0.5
Summary: Calculates ligand strain of small molecules from their docked poses.
Author-email: Ewan Wallace <erw@wallace2.com>
License-Expression: Apache-2.0
Project-URL: Homepage, https://github.com/prescient-design/StrainRelief
Requires-Python: >=3.11
License-File: LICENSE
Requires-Dist: rdkit
Requires-Dist: ase
Requires-Dist: numpy
Requires-Dist: pandas
Requires-Dist: omegaconf
Requires-Dist: hydra-core
Requires-Dist: pyarrow
Requires-Dist: fastparquet
Requires-Dist: universal-pathlib
Requires-Dist: boto3
Requires-Dist: loguru
Requires-Dist: mace-torch
Requires-Dist: rich
Provides-Extra: dev
Requires-Dist: pytest; extra == "dev"
Requires-Dist: pytest-cov; extra == "dev"
Requires-Dist: pre-commit; extra == "dev"
Requires-Dist: ipykernel; extra == "dev"
Dynamic: license-file
